karrio/server/apps/__init__.py
karrio/server/apps/admin.py
karrio/server/apps/apps.py
karrio/server/apps/filters.py
karrio/server/apps/models.py
karrio/server/apps/serializers.py
karrio/server/apps/tests.py
karrio/server/apps/views.py
karrio/server/apps/migrations/0001_initial.py
karrio/server/apps/migrations/__init__.py
karrio/server/graph/schemas/__init__.py
karrio/server/graph/schemas/apps/__init__.py
karrio/server/graph/schemas/apps/inputs.py
karrio/server/graph/schemas/apps/mutations.py
karrio/server/graph/schemas/apps/types.py
karrio.server.apps-2023.1.dist-info/METADATA
karrio.server.apps-2023.1.dist-info/WHEEL
karrio.server.apps-2023.1.dist-info/top_level.txt
karrio.server.apps-2023.1.dist-info/RECORD
